pinax/__init__.py
pinax/events/__init__.py
pinax/events/admin.py
pinax/events/apps.py
pinax/events/models.py
pinax/events/specs.py
pinax/events/utils.py
pinax/events/migrations/0001_initial.py
pinax/events/migrations/0002_event_title.py
pinax/events/migrations/0003_event_url.py
pinax/events/migrations/0004_auto_20160905_1144.py
pinax/events/migrations/__init__.py
pinax/events/templatetags/__init__.py
pinax/events/templatetags/pinax_events_tags.py
pinax/events/tests/__init__.py
pinax/events/tests/tests.py
pinax_events-3.0.0.dist-info/AUTHORS
pinax_events-3.0.0.dist-info/LICENSE
pinax_events-3.0.0.dist-info/METADATA
pinax_events-3.0.0.dist-info/WHEEL
pinax_events-3.0.0.dist-info/top_level.txt
pinax_events-3.0.0.dist-info/RECORD
